MANIFEST.in
setup.cfg
setup.py
bdworkbench/__init__.py
bdworkbench/__main__.py
bdworkbench/bdwb.py
bdworkbench/constants.py
bdworkbench/inmem_store.py
bdworkbench/version.py
bdworkbench.egg-info/PKG-INFO
bdworkbench.egg-info/SOURCES.txt
bdworkbench.egg-info/dependency_links.txt
bdworkbench.egg-info/entry_points.txt
bdworkbench.egg-info/not-zip-safe
bdworkbench.egg-info/requires.txt
bdworkbench.egg-info/top_level.txt
bdworkbench/appbuild/.DS_Store
bdworkbench/appbuild/.gitignore
bdworkbench/appbuild/decompress_v3.sh
bdworkbench/appbuild/decompress_v4.sh
bdworkbench/appbuild/package_v3.sh
bdworkbench/appbuild/config_scripts_common/appjob
bdworkbench/appbuild/config_scripts_common/logging.sh
bdworkbench/appbuild/config_scripts_common/macros.sh
bdworkbench/appbuild/config_scripts_common/startscript
bdworkbench/appbuild/config_scripts_common/systemd.service
bdworkbench/appbuild/config_scripts_common/utils.sh
bdworkbench/appconfig/__init__.py
bdworkbench/appconfig/appconfig_download.py
bdworkbench/appconfig/appconfig_file.py
bdworkbench/appconfig/appconfig_init.py
bdworkbench/appconfig/appconfig_list.py
bdworkbench/appconfig/appconfig_package.py
bdworkbench/appconfig/appconfig_autogen/__init__.py
bdworkbench/appconfig/appconfig_autogen/addfile.py
bdworkbench/appconfig/appconfig_autogen/append.py
bdworkbench/appconfig/appconfig_autogen/execute.py
bdworkbench/appconfig/appconfig_autogen/perms.py
bdworkbench/appconfig/appconfig_autogen/replace.py
bdworkbench/appconfig/appconfig_autogen/services.py
bdworkbench/appconfig/appconfig_autogen/sourcefile.py
bdworkbench/baseimg/__init__.py
bdworkbench/baseimg/__init__.pyc
bdworkbench/baseimg/baseimg_init.py
bdworkbench/baseimg/baseimg_init.pyc
bdworkbench/baseimg/centos6/Makefile
bdworkbench/baseimg/centos6/build.sh
bdworkbench/baseimg/centos6/template/.gitignore
bdworkbench/baseimg/centos6/template/Dockerfile.template
bdworkbench/baseimg/centos6/template/limits-90-nproc.conf
bdworkbench/baseimg/centos6/template/supervisord.conf
bdworkbench/baseimg/centos7/.DS_Store
bdworkbench/baseimg/centos7/Makefile
bdworkbench/baseimg/centos7/build.sh
bdworkbench/baseimg/centos7/template/.gitignore
bdworkbench/baseimg/centos7/template/Dockerfile.template
