Metadata-Version: 1.1
Name: bdworkbench
Version: 3.4
Summary: Appstore SDK for BlueData EPIC platform.
Home-page: https://github.com/bluedatainc/catalogsdk
Author: BlueData Software, Inc.
Author-email: support@bluedata.com
License: UNKNOWN
Keywords: BlueData,appstore,catalog,EPIC
Platform: UNKNOWN
Classifier: Environment :: Console
Classifier: Natural Language :: English
Classifier: Programming Language :: Python
Classifier: Intended Audience :: Developers
Classifier: Development Status :: 5 - Production/Stable
Classifier: License :: OSI Approved :: Apache Software License
Classifier: Programming Language :: Python :: Implementation :: CPython
